paketmutfak/__init__.py
paketmutfak/db/LogDbBase.py
paketmutfak/db/__init__.py
paketmutfak/db/dynamo_db_base_class.py
paketmutfak/db/sql_db_base_class.py
paketmutfak/mail/__init__.py
paketmutfak/mail/aws_ses.py
paketmutfak/utils/__init__.py
paketmutfak/utils/constants/PM.py
paketmutfak/utils/constants/__init__.py
paketmutfak/utils/constants/error_codes.py
paketmutfak/utils/constants/log_levels.py
paketmutfak/utils/constants/parameters.py
paketmutfak/utils/constants/platforms.py
paketmutfak/utils/constants/products.py
paketmutfak/utils/formats/__init__.py
paketmutfak/utils/formats/order.py
paketmutfak/utils/functions/__init__.py
paketmutfak/utils/functions/general.py
paketmutfak/utils/functions/regions.py
paketmutfak-1.1.42.dist-info/LICENSE.txt
paketmutfak-1.1.42.dist-info/METADATA
paketmutfak-1.1.42.dist-info/WHEEL
paketmutfak-1.1.42.dist-info/top_level.txt
paketmutfak-1.1.42.dist-info/RECORD
