Metadata-Version: 2.1
Name: paketmutfak
Version: 1.1.42
Summary: Testing installation of Package
Home-page: https://github.com/PaketMutfak/PaketMutfak-Lib-Test
Author: Paket Mutfak
Author-email: dev@paketmutfak.com.tr
License: MIT
Project-URL: Bug Tracker, https://github.com/PaketMutfak/PaketMutfak-Lib-Test/issues
License-File: LICENSE.txt
Requires-Dist: requests
Requires-Dist: boto3
Requires-Dist: mysql-connector
Requires-Dist: uuid
Requires-Dist: datetime
Requires-Dist: iso8601
Requires-Dist: slugify
Requires-Dist: PyJWT
Requires-Dist: beartype
Requires-Dist: flask
Requires-Dist: python-ulid
